uwuipy/__init__.py
uwuipy/__main__.py
uwuipy/uwuipy.py
uwuipy-0.1.10.dist-info/AUTHORS
uwuipy-0.1.10.dist-info/LICENSE
uwuipy-0.1.10.dist-info/METADATA
uwuipy-0.1.10.dist-info/WHEEL
uwuipy-0.1.10.dist-info/RECORD
