Metadata-Version: 2.3
Name: uwuipy
Version: 0.1.10
Summary: Allows the easy implementation of uwuifying words for applications like Discord bots and websites
License: MIT
Author: Cuprum77
Requires-Python: >=3.10,<4.0
Classifier: License :: OSI Approved :: MIT License
Classifier: Programming Language :: Python :: 3
Classifier: Programming Language :: Python :: 3.10
Classifier: Programming Language :: Python :: 3.11
Classifier: Programming Language :: Python :: 3.12
Classifier: Programming Language :: Python :: 3.13
Project-URL: homepage, https://github.com/Cuprum77/uwuipy
